pandas_indexing/__init__.py
pandas_indexing/accessors.py
pandas_indexing/arithmetics.py
pandas_indexing/core.py
pandas_indexing/py.typed
pandas_indexing/selectors.py
pandas_indexing/types.py
pandas_indexing/units.py
pandas_indexing/utils.py
pandas_indexing/datasets/__init__.py
pandas_indexing/datasets/remindhighre_power.csv
pandas_indexing/iamc/__init__.py
pandas_indexing/iamc/resolver.py
pandas_indexing-0.6.3.dist-info/LICENSE
pandas_indexing-0.6.3.dist-info/METADATA
pandas_indexing-0.6.3.dist-info/WHEEL
pandas_indexing-0.6.3.dist-info/top_level.txt
pandas_indexing-0.6.3.dist-info/RECORD
