Metadata-Version: 2.2
Name: pandas-indexing
Version: 0.6.3
Summary: Helpers to facilitate working with pandas indices in particular multiindices
Author-email: Jonas Hörsch <coroa@posteo.de>
License: MIT
Project-URL: changelog, https://github.com/coroa/pandas-indexing/blob/main/CHANGELOG.rst
Project-URL: documentation, https://pandas-indexing.readthedocs.io/en/latest/
Project-URL: homepage, https://github.com/coroa/pandas-indexing
Project-URL: repository, https://github.com/coroa/pandas-indexing.git
Keywords: pandas
Classifier: Development Status :: 4 - Beta
Classifier: License :: OSI Approved :: MIT License
Classifier: Intended Audience :: Science/Research
Classifier: Natural Language :: English
Classifier: Operating System :: POSIX
Classifier: Operating System :: MacOS
Classifier: Operating System :: Microsoft
Classifier: Programming Language :: Python :: 3
Classifier: Programming Language :: Python :: 3.9
Classifier: Programming Language :: Python :: 3.10
Classifier: Programming Language :: Python :: 3.11
Classifier: Programming Language :: Python :: 3.12
Classifier: Programming Language :: Python :: 3.13
Requires-Python: <4,>=3.9
License-File: LICENSE
Requires-Dist: pandas>=1.2
Requires-Dist: deprecated
Requires-Dist: attrs
Provides-Extra: units
Requires-Dist: pint>=0.21; extra == "units"
Requires-Dist: openscm-units; extra == "units"
